py_simple_image_editor/__init__.py
py_simple_image_editor/__main__.py
py_simple_image_editor/py_simple_image_editor.py
py_simple_image_editor/version.py
py_simple_image_editor/__pycache__/__init__.cpython-311.pyc
py_simple_image_editor/__pycache__/py_simple_image_editor.cpython-311.pyc
py_simple_image_editor/__pycache__/version.cpython-311.pyc
py_simple_image_editor/pixel/__init__.py
py_simple_image_editor/pixel/base_tile.py
py_simple_image_editor/pixel/clipboard.py
py_simple_image_editor/pixel/layer_manager.py
py_simple_image_editor/pixel/layer_viewer.py
py_simple_image_editor/pixel/pallete_frame.py
py_simple_image_editor/pixel/pixel.py
py_simple_image_editor/pixel/pixel_canvas.py
py_simple_image_editor/pixel/save_window.py
py_simple_image_editor/pixel/tool_bar.py
py_simple_image_editor/pixel/tool_box.py
py_simple_image_editor/pixel/tool_controller.py
py_simple_image_editor/pixel/__pycache__/__init__.cpython-311.pyc
py_simple_image_editor/pixel/__pycache__/base_tile.cpython-311.pyc
py_simple_image_editor/pixel/__pycache__/clipboard.cpython-311.pyc
py_simple_image_editor/pixel/__pycache__/image_viewer.cpython-311.pyc
py_simple_image_editor/pixel/__pycache__/layer_manager.cpython-311.pyc
py_simple_image_editor/pixel/__pycache__/layer_viewer.cpython-311.pyc
py_simple_image_editor/pixel/__pycache__/pallete_frame.cpython-311.pyc
py_simple_image_editor/pixel/__pycache__/pixel.cpython-311.pyc
py_simple_image_editor/pixel/__pycache__/pixel_canvas.cpython-311.pyc
py_simple_image_editor/pixel/__pycache__/save_window.cpython-311.pyc
py_simple_image_editor/pixel/__pycache__/tool_bar.cpython-311.pyc
py_simple_image_editor/pixel/__pycache__/tool_box.cpython-311.pyc
py_simple_image_editor/pixel/__pycache__/tool_controller.cpython-311.pyc
py_simple_image_editor-0.0.5.dist-info/LICENSE
py_simple_image_editor-0.0.5.dist-info/METADATA
py_simple_image_editor-0.0.5.dist-info/WHEEL
py_simple_image_editor-0.0.5.dist-info/top_level.txt
py_simple_image_editor-0.0.5.dist-info/RECORD
