Metadata-Version: 2.1
Name: py-simple-image-editor
Version: 0.0.5
Summary: A basic pixel art / pixel gif editor.
Author-email: Andrew Spangler <AndrewSpangler@users.noreply.github.com>
License: LICENSE
Project-URL: homepage, https://GitHub.com/AndrewSpangler/py_simple_image_editor/
Project-URL: bug tracker, https://GitHub.com/AndrewSpangler/py_simple_image_editor/issues
Project-URL: documentation, https://GitHub.com/AndrewSpangler/py_simple_image_editor/
Project-URL: repository, https://GitHub.com/AndrewSpangler/py_simple_image_editor/
Keywords: image,editor,gif,animated,animation
Classifier: Development Status :: 1 - Planning
Classifier: Environment :: Console
Classifier: License :: OSI Approved :: GNU General Public License v3 or later (GPLv3+)
Classifier: Natural Language :: English
Classifier: Operating System :: OS Independent
Classifier: Programming Language :: Python :: 3.11
Requires-Python: >=3.11
License-File: LICENSE
Requires-Dist: py-simple-ttk
Requires-Dist: pillow
Requires-Dist: numpy
